hvloop/__init__.py
hvloop/handle.pxd
hvloop/handle.pyx
hvloop/loop.c
hvloop/loop.cp38-win_amd64.pyd
hvloop/loop.pxd
hvloop/loop.pyx
hvloop/requests.pyx
hvloop/server.pxd
hvloop/server.pyx
hvloop/transport.pxd
hvloop/transport.pyx
hvloop/includes/__init__.py
hvloop/includes/hv.pxd
hvloop/includes/python.pxd
hvloop-0.0.2.dist-info/METADATA
hvloop-0.0.2.dist-info/WHEEL
hvloop-0.0.2.dist-info/top_level.txt
hvloop-0.0.2.dist-info/RECORD
